.DS_Store
mlvis/__init__.py
mlvis/class_builder.py
mlvis/jrequirements.json
mlvis/utils.py
mlvis/widget.py
mlvis/widget_builder.py
mlvis/static/extension.js
mlvis/static/index.js
mlvis/static/index.js.map
mlvis/static/styled-components.js
mlvis/static/styled-components.js.map
mlvis/widget_ext/FeatureListView.py
mlvis/widget_ext/GraphBuilder.py
mlvis/widget_ext/Manifold.py
mlvis/widget_ext/MultiWayPlot.py
mlvis/widget_ext/StackedCalendar.py
mlvis/widget_ext/__init__.py
mlvis-0.1.0.data/data/share/jupyter/nbextensions/mlvis/extension.js
mlvis-0.1.0.data/data/share/jupyter/nbextensions/mlvis/index.js
mlvis-0.1.0.data/data/share/jupyter/nbextensions/mlvis/index.js.map
mlvis-0.1.0.data/scripts/jpip
mlvis-0.1.0.data/scripts/jpip.py
mlvis-0.1.0.dist-info/LICENSE
mlvis-0.1.0.dist-info/METADATA
mlvis-0.1.0.dist-info/WHEEL
mlvis-0.1.0.dist-info/top_level.txt
mlvis-0.1.0.dist-info/RECORD
