Metadata-Version: 2.1
Name: mlvis
Version: 0.1.0
Summary: A wrapper around react components for use in jupyter notebooks
Home-page: https://github.com/uber/manifold.git
Author: Hong Wang
Author-email: hongw@uber.com
License: Apache License 2.0
Keywords: data,visualization,machine learning
Platform: UNKNOWN
Classifier: Development Status :: 3 - Alpha
Classifier: Intended Audience :: Developers
Classifier: Intended Audience :: Science/Research
Classifier: Topic :: Multimedia :: Graphics
Classifier: License :: OSI Approved :: Apache Software License
Classifier: Programming Language :: Python :: 2.7
Classifier: Programming Language :: Python :: 3
Classifier: Programming Language :: Python :: 3.3
Classifier: Programming Language :: Python :: 3.4
Classifier: Programming Language :: Python :: 3.5
Classifier: Programming Language :: Python :: 3.6
Classifier: Programming Language :: Python :: 3.7
Classifier: Framework :: Jupyter
Requires-Dist: traitlets
Requires-Dist: ipywidgets
Requires-Dist: pandas
